[
  {
    "capture_time": "2022-08-12",
    "base_recipe": "Gongura Fries",
    "feed": 0
  },
  {
    "capture_time": "2022-08-12",
    "base_recipe": "something",
    "feed": 1
  },
  {
    "capture_time": "2022-08-12",
    "base_recipe": "something",
    "feed": 1
  },
  {
    "capture_time": "2022-08-12",
    "base_recipe": "something",
    "feed": 0
  },
  {
    "capture_time": "2022-08-12",
    "base_recipe": "Thunder1",
    "feed": 1
  },
  {
    "capture_time": "2022-08-13",
    "base_recipe": "Spicy Tomato Rice (Recipe)",
    "feed": 1
  },
  {
    "capture_time": "2022-08-13",
    "base_recipe": "Spicy Tomato Rice (Recipe)",
    "feed": 0
  },
  {
    "capture_time": "2022-08-13",
    "base_recipe": "Thunder2",
    "feed": 1
  },
  {
    "capture_time": "2022-08-13",
    "base_recipe": "Spicy Tomato Rice (Recipe)",
    "feed": 1
  },
  {
    "capture_time": "2022-08-13",
    "base_recipe": "Spicy Tomato Rice (Recipe)",
    "feed": 0
  },
  {
    "capture_time": "2022-08-13",
    "base_recipe": "Cauliflower Leaves Chutney (Recipe in Hindi)",
    "feed": 1
  },
  {
    "capture_time": "2022-08-13",
    "base_recipe": "Cauliflower Leaves Chutney (Recipe in Hindi)",
    "feed": 0
  },
  {
    "capture_time": "2022-08-13",
    "base_recipe": "Ragi Semiya Upma Recipe - Ragi Millet Vermicelli Breakfast",
    "feed": 1
  },
  {
    "capture_time": "2022-08-13",
    "base_recipe": "Ragi Semiya Upma Recipe - Ragi Millet Vermicelli Breakfast",
    "feed": 0
  },
  {
    "capture_time": "2022-08-13",
    "base_recipe": "Ragi Semiya Upma Recipe - Ragi Millet Vermicelli Breakfast",
    "feed": 1
  },
  {
    "capture_time": "2022-08-13",
    "base_recipe": "Ragi Semiya Upma Recipe - Ragi Millet Vermicelli Breakfast",
    "feed": 0
  },
  {
    "capture_time": "2022-08-13",
    "base_recipe": "Ragi Semiya Upma Recipe - Ragi Millet Vermicelli Breakfast",
    "feed": 1
  },
  {
    "capture_time": "2022-08-13",
    "base_recipe": "Vegan Navratan Korma Recipe",
    "feed": 0
  },
  {
    "capture_time": "2022-08-13",
    "base_recipe": "Rajgira Paneer Paratha Recipe (Navratri Fasting/Vrat Recipe)",
    "feed": 1
  },
  {
    "capture_time": "2022-08-13",
    "base_recipe": "Whole Wheat Spinach And Tofu Paratha Recipe",
    "feed": 1
  },
  {
    "capture_time": "2022-08-13",
    "base_recipe": "Vazhakkai Varuval Recipe- Raw Banana Roast Recipe",
    "feed": 0
  },
  {
    "capture_time": "2022-08-13",
    "base_recipe": "Bihari Suran Chutney Recipe (Bihar Style Elephant Yam Chutney)",
    "feed": 1
  },
  {
    "capture_time": "2022-08-13",
    "base_recipe": "Bihari Suran Chutney Recipe (Bihar Style Elephant Yam Chutney)",
    "feed": 1
  }
]